README.txt
setup.cfg
setup.py
aha/__init__.py
aha.egg-info/PKG-INFO
aha.egg-info/SOURCES.txt
aha.egg-info/dependency_links.txt
aha.egg-info/requires.txt
aha.egg-info/top_level.txt
aha.egg-info/zip-safe
aha/auth/__init__.py
aha/auth/appengine.py
aha/auth/base.py
aha/controller/__init__.py
aha/controller/basecontroller.py
aha/controller/baseview.py
aha/controller/decorator.py
aha/controller/helper.py
aha/controller/makocontroller.py
aha/controller/makoemailengine.py
aha/controller/translation.py
aha/controller/util.py
aha/dispatch/__init__.py
aha/dispatch/dispatcher.py
aha/dispatch/router.py
aha/model/__init__.py
aha/model/cachedmodel.py
aha/model/lazyloadingmodel.py
aha/modelcontroller/__init__.py
aha/modelcontroller/crudcontroller.py
aha/modelcontroller/formcontrol.py
aha/session/__init__.py
aha/session/datastore.py
aha/session/memcache.py
aha/widget/__init__.py
aha/widget/field.py
aha/widget/form.py
aha/widget/handler.py
aha/wsgi/__init__.py
aha/wsgi/appinit.py
aha/wsgi/cwsgiapp.py
aha/wsgi/debug/__init__.py
aha/wsgi/debug/utils.py